coincappy/__init__.py
coincappy/api.py
coincappy-0.1.0.dist-info/LICENSE
coincappy-0.1.0.dist-info/METADATA
coincappy-0.1.0.dist-info/WHEEL
coincappy-0.1.0.dist-info/top_level.txt
coincappy-0.1.0.dist-info/RECORD
