Metadata-Version: 2.1
Name: coincappy
Version: 0.1.0
Summary: Simple Python wrapper around CoinMarketCap free endpoints
Home-page: https://github.com/kiwioverseas/coincappy
License: MIT
Keywords: crypto,cryptocurrency,coinmarketcap
Platform: UNKNOWN
Classifier: License :: OSI Approved :: MIT License
Classifier: Operating System :: OS Independent
Classifier: Programming Language :: Python :: 3
Classifier: Programming Language :: Python :: 3.6
Requires-Python: >=3.6
Requires-Dist: requests
